setup.py
matrixmath/__init__.py
matrixmath.egg-info/PKG-INFO
matrixmath.egg-info/SOURCES.txt
matrixmath.egg-info/dependency_links.txt
matrixmath.egg-info/not-zip-safe
matrixmath.egg-info/top_level.txt