Metadata-Version: 1.0
Name: matrixmath
Version: 1.0
Summary: A simple, No frills library for basic matrix operations.
Home-page: https://github.com/Jackojc/matrixmath
Author: Jack Clarke
Author-email: jackojc@gmail.com
License: MIT
Platform: UNKNOWN
